COPYING
MANIFEST.in
NOTICE
README
aioeventlet.py
runtests.py
setup.py
tox.ini
doc/Makefile
doc/changelog.rst
doc/conf.py
doc/index.rst
doc/make.bat
doc/openstack.rst
doc/poplar_hawk-moth.jpg
doc/status.rst
doc/using.rst
faust_aioeventlet.egg-info/PKG-INFO
faust_aioeventlet.egg-info/SOURCES.txt
faust_aioeventlet.egg-info/dependency_links.txt
faust_aioeventlet.egg-info/requires.txt
faust_aioeventlet.egg-info/top_level.txt
tests/__init__.py
tests/test_eventlet.py
tests/test_greenlet.py