Metadata-Version: 2.1
Name: faust-aioeventlet
Version: 0.6
Summary: asyncio event loop scheduling callbacks in eventlet.
Home-page: http://aioeventlet.readthedocs.org/
Author: Victor Stinner
Author-email: victor.stinner@gmail.com
License: Apache License 2.0
Classifier: Programming Language :: Python
Classifier: Programming Language :: Python :: 3
Classifier: License :: OSI Approved :: Apache Software License
License-File: COPYING
License-File: NOTICE
